hail_scripts/__init__.py
seqr_loader_batch/__init__.py
seqr_loader_batch/driver.py
seqr_loader_batch/load.py
seqr_loader_batch-1.0.2.data/scripts/load.py
seqr_loader_batch-1.0.2.dist-info/LICENSE
seqr_loader_batch-1.0.2.dist-info/METADATA
seqr_loader_batch-1.0.2.dist-info/WHEEL
seqr_loader_batch-1.0.2.dist-info/top_level.txt
seqr_loader_batch-1.0.2.dist-info/RECORD
