Metadata-Version: 2.1
Name: seqr-loader-batch
Version: 1.0.2
Summary: The hail scripts in this repo can be used to pre-process variant callsets and export them to elasticsearch
Home-page: https://github.com/populationgenomics/hail-elasticsearch-pipelines
License: MIT
Keywords: bioinformatics
Platform: UNKNOWN
Classifier: Environment :: Console
Classifier: Intended Audience :: Science/Research
Classifier: License :: OSI Approved :: GNU General Public License v3 (GPLv3)
Classifier: Natural Language :: English
Classifier: Operating System :: MacOS :: MacOS X
Classifier: Operating System :: POSIX
Classifier: Operating System :: Unix
Classifier: Programming Language :: Python
Classifier: Topic :: Scientific/Engineering
Classifier: Topic :: Scientific/Engineering :: Bio-Informatics
